spreadlinks/__init__.py
spreadlinks/linklibrarylib.py
spreadlinks/models.py
spreadlinks/static/style/League Gothic.otf
spreadlinks/static/style/base.css
spreadlinks/static/style/front.css
spreadlinks/static/style/jeremyday-bg-dark.png
spreadlinks/static/style/jeremyday-bg-pale.png
spreadlinks/static/style/jeremyday-bg.gif
spreadlinks/static/style/jeremyday.css
spreadlinks/templates/jeremyday/base.html
spreadlinks/templates/spreadlinks/base.html
spreadlinks/templates/spreadlinks/library-detail.html
spreadlinks/templates/spreadlinks/library-list.html
spreadlinks/urls.py
spreadlinks/views.py
spreadlinks-0.5.0.dist-info/LICENCE.txt
spreadlinks-0.5.0.dist-info/METADATA
spreadlinks-0.5.0.dist-info/WHEEL
spreadlinks-0.5.0.dist-info/RECORD
