Metadata-Version: 2.3
Name: spreadlinks
Version: 0.5.0
Summary: Django app for displaying links to resources with simple tags-based filtering
License: MIT
Author: Damian Cugley
Author-email: pdc@alleged.org.uk
Requires-Python: >=3.13,<4
Classifier: Development Status :: 3 - Alpha
Classifier: Programming Language :: Python :: 3
Classifier: Programming Language :: Python :: 3.13
Classifier: Framework :: Django :: 5.2
Classifier: Operating System :: OS Independent
Requires-Dist: django (>=5.2.5,<6.0.0)
Requires-Dist: markdown (>=3.8.2,<4.0.0)
